never_miss_a_bill_again-1.6.0.dist-info/licenses/LICENSE.txt
nmba/cli.py
nmba/data/crud.py
nmba/data/database.py
nmba/data/models.py
nmba/data/schemas.py
never_miss_a_bill_again-1.6.0.dist-info/METADATA
never_miss_a_bill_again-1.6.0.dist-info/WHEEL
never_miss_a_bill_again-1.6.0.dist-info/entry_points.txt
never_miss_a_bill_again-1.6.0.dist-info/top_level.txt
never_miss_a_bill_again-1.6.0.dist-info/RECORD
