Metadata-Version: 2.4
Name: never-miss-a-bill-again
Version: 1.6.0
Summary: Never miss a bill again
Requires-Python: >=3.12
License-File: LICENSE.txt
Requires-Dist: sqlalchemy
Requires-Dist: alembic
Requires-Dist: apprise
Requires-Dist: pydantic
Requires-Dist: structlog
Requires-Dist: typer
Requires-Dist: rich
Requires-Dist: click
Provides-Extra: dev
Requires-Dist: pre-commit; extra == "dev"
Requires-Dist: pytest; extra == "dev"
Requires-Dist: python-semantic-release; extra == "dev"
Requires-Dist: black; extra == "dev"
Dynamic: license-file
